gf2_lin_algebra/__init__.py
gf2_lin_algebra/gf2_lin_algebra.cpython-314t-x86_64-linux-musl.so
gf2_lin_algebra-1.0.1.dist-info/METADATA
gf2_lin_algebra-1.0.1.dist-info/WHEEL
gf2_lin_algebra-1.0.1.dist-info/licenses/LICENSE.md
gf2_lin_algebra.libs/libgcc_s-6d2d9dc8.so.1
gf2_lin_algebra-1.0.1.dist-info/RECORD
