Metadata-Version: 2.4
Name: gf2_lin_algebra
Version: 1.0.1
Classifier: Programming Language :: Rust
Classifier: Programming Language :: Python :: Implementation :: CPython
Classifier: Programming Language :: Python :: Implementation :: PyPy
License-File: LICENSE.md
Summary: A linear algebra package to compute operations in GF(2).
Home-Page: https://github.com/LucaBonamino/gf2_lin_algebra
Requires-Python: >=3.8
Project-URL: Documentation, https://lucabonamino.github.io/gf2_lin_algebra/
Project-URL: Issues, https://github.com/LucaBonamino/gf2_lin_algebra/issues
Project-URL: Source, https://github.com/LucaBonamino/gf2_lin_algebra
